twstocks_crawler/__init__.py
twstocks_crawler/log.py
twstocks_crawler/main.py
twstocks_crawler/utils.py
twstocks_crawler/version.py
twstocks_crawler/repositories/__init__.py
twstocks_crawler/repositories/industry_diff.py
twstocks_crawler/repositories/stock_profiles.py
twstocks_crawler-0.0.7.dist-info/METADATA
twstocks_crawler-0.0.7.dist-info/WHEEL
twstocks_crawler-0.0.7.dist-info/top_level.txt
twstocks_crawler-0.0.7.dist-info/RECORD
