Metadata-Version: 2.1
Name: twstocks-crawler
Version: 0.0.7
Summary: TWStock profiles crawler
Home-page: https://github.com/sunaley/stocks
Author: Sunaley
Author-email: sunaley@gmail.com
Classifier: Programming Language :: Python :: 3
Classifier: License :: OSI Approved :: MIT License
Classifier: Operating System :: OS Independent
Requires-Python: >=3.9
Requires-Dist: requests
Requires-Dist: lxml
Requires-Dist: pandas
Requires-Dist: aiohttp
Requires-Dist: aiohttp-socks
Requires-Dist: charset-normalizer (==2.0.0)
